Workbook

Sheet Dashboard
A1: Dashboard QA — Plan de test TOMSEN
A3: Indicateur | B3: Valeur | D3: Cas de test par Sprint
A4: Exigences (revue) | B4: =COUNTA('Revue exigences QA'!$A$2:$A$1000) -> 42 | D4: Sprint | E4: Nb
A5: Cas de test (total) | B5: =COUNTA('Plan de test par Sprint'!$B$2:$B$1000) -> 48 | D5: Sprint 1 | E5: =COUNTIF('Plan de test par Sprint'!$A$2:$A$1000,"Sprint 1") -> 20
A6: Cas de test — Critiques | B6: =COUNTIF('Plan de test par Sprint'!$E$2:$E$1000,"Critique") -> 16 | D6: Sprint 2 | E6: =COUNTIF('Plan de test par Sprint'!$A$2:$A$1000,"Sprint 2") -> 16
A7: Cas de test — Élevés | B7: =COUNTIF('Plan de test par Sprint'!$E$2:$E$1000,"Élevée") -> 22 | D7: Sprint 3 | E7: =COUNTIF('Plan de test par Sprint'!$A$2:$A$1000,"Sprint 3") -> 4
A8: Cas de test — Moyens | B8: =COUNTIF('Plan de test par Sprint'!$E$2:$E$1000,"Moyenne") -> 10 | D8: Sprint 4 | E8: =COUNTIF('Plan de test par Sprint'!$A$2:$A$1000,"Sprint 4") -> 5
A9: Cas de test — Exécutés (Passé) | B9: =COUNTIF('Plan de test par Sprint'!$G$2:$G$1000,"Passé") -> 0 | D9: Sprint 5 | E9: =COUNTIF('Plan de test par Sprint'!$A$2:$A$1000,"Sprint 5") -> 3
A12: Cas de test par criticité | D12: Cas de test par statut
A13: Criticité | B13: Nb | D13: Statut | E13: Nb
A14: Critique | B14: =COUNTIF('Plan de test par Sprint'!$E$2:$E$1000,"Critique") -> 16 | D14: Non exécuté | E14: =COUNTIF('Plan de test par Sprint'!$G$2:$G$1000,"Non exécuté") -> 48
A15: Élevée | B15: =COUNTIF('Plan de test par Sprint'!$E$2:$E$1000,"Élevée") -> 22 | D15: En cours | E15: =COUNTIF('Plan de test par Sprint'!$G$2:$G$1000,"En cours") -> 0
A16: Moyenne | B16: =COUNTIF('Plan de test par Sprint'!$E$2:$E$1000,"Moyenne") -> 10 | D16: Passé | E16: =COUNTIF('Plan de test par Sprint'!$G$2:$G$1000,"Passé") -> 0
A17: Faible | B17: =COUNTIF('Plan de test par Sprint'!$E$2:$E$1000,"Faible") -> 0 | D17: Échoué | E17: =COUNTIF('Plan de test par Sprint'!$G$2:$G$1000,"Échoué") -> 0
A18: Informative | B18: =COUNTIF('Plan de test par Sprint'!$E$2:$E$1000,"Informative") -> 0 | D18: Bloqué | E18: =COUNTIF('Plan de test par Sprint'!$G$2:$G$1000,"Bloqué") -> 0
D19: NA | E19: =COUNTIF('Plan de test par Sprint'!$G$2:$G$1000,"NA") -> 0

Sheet Revue exigences QA
A1: TOM | B1: Domaine | C1: Criticité | D1: Ambiguïté | E1: Question | F1: Impact | G1: Statut | H1: Owner
A2: TOM01-AUT-01 | B2: Authentification | C2: Élevée | D2: Gestion multi-profils / comptes joints non mentionnée. | E2: V1 gère-t-elle 1 seul profil par utilisateur ou plusieurs identités (ex : compte joint, mandataire) ? | F2: Risque de rework données/IHM | G2: A clarifier | H2: Elsa
A3: TOM01-DON-01 | B3: Données/BDD | C3: Élevée | D3: Périmètre des données identité non listé (obligatoire vs optionnel). | E3: Quelles données personnelles sont obligatoires/optionnelles et quelles données sont interdites de stockage (RGPD) ? Quelle est la liste complète des champs obligatoires et optionnels pour créer un compte (email, téléphone, adresse, etc.) | F3: Tests incomplets + risque conformité | G3: A clarifier | H3: Elsa
A4: TOM01-DON-01 | B4: Sécurité/Conformité | C4: Critique | D4: Protéger les comptes contre les attaques tout en restant utilisable. | E4: Quelle est la politique de blocage de compte et de déconnexion automatique (nombre d’essais ratés, durée de blocage, timeout de session) ? | F4: Risque sécurité/RGPD + non‑conformité + blocage recette. | G4: A clarifier | H4: Elsa
A5: TOM01-SEC-01 | B5: IHM | C5: Élevée | D5: Empêcher l'ouverture de compte par des clients non éligibles. | E5: Y a‑t‑il des règles d’éligibilité particulières à contrôler à la création du compte (âge minimum, pays autorisés, situation de résidence) ? Si oui, lesquelles ? | F5: Tests UX incomplets + incompréhension utilisateur. | G5: A clarifier | H5: Elsa
A6: TOM01-SEC-01 | B6: Sécurité/Conformité | C6: Élevée | D6: Traçabilité/audit non précisée. | E6: Quels événements doivent être journalisés (création compte, changement MDP, activation 2FA/biométrie) et quel niveau de détail ? | F6: Impossible de valider exigences sécurité | G6: A clarifier | H6: Elsa
A7: TOM06-DON-01 | B7: Données/BDD | C7: Élevée | D7: Stockage des données utilisateur non cadré. | E7: Quelles informations doivent être stockées (obligatoires) et lesquelles ne doivent jamais l’être (RGPD) ? | F7: Non conformité + tests impossibles | G7: A clarifier | H7: Elsa
A8: TOM06-FLD-01 | B8: Données/BDD | C8: Critique | D8: “Prénom : champ numérique” incohérent. | E8: Confirme‑t‑on que Nom/Prénom sont des champs texte (accents/traits d’union) et quelles validations ? | F8: Blocage dev/tests | G8: A clarifier | H8: Elsa
A9: TOM06-FLD-02 | B9: IHM | C9: Élevée | D9: Format date de naissance “JJ/MM.AAAA” ambigu. | E9: Quel format exact attendu (JJ/MM/AAAA ou JJ.MM.AAAA) et quels contrôles (âge minimum, cohérence) ? | F9: Cas de test non déterministes | G9: A clarifier | H9: Elsa
A10: TOM06-SEC-01 | B10: Sécurité/Conformité | C10: Critique | D10: Assurer une sécurité suffisante des mots de passe. Règles MDP incomplètes (verrouillage, essais). | E10: Quel est le nombre d’essais avant blocage et la durée de verrouillage, et y a-t-il un anti‑bruteforce (rate‑limit/captcha) ? Quelles sont exactement les règles de mot de passe à appliquer (longueur minimale, types de caractères, durée de validité, nombre d’essais avant blocage) ? | F10: Risque sécurité majeur Risque sécurité/RGPD + non‑conformité + blocage recette. | G10: A clarifier | H10: Elsa
A11: TOM07-DON-01 | B11: Données/BDD | C11: Élevée | D11: Éviter les risques de performance et de stockage lors des uploads. “Enregistrer en base les informations” sans détail. | E11: Quelle est la taille maximale autorisée par fichier et le nombre maximum de documents par type pour un utilisateur ? Quelles données sont enregistrées (métadonnées, statut, lien fichier) et où sont stockés les fichiers (local vs serveur) ? | F11: Risque archi + RGPD Risque perf/volumétrie + données incohérentes + tests BDD impossibles. | G11: A clarifier | H11: Elsa
A12: TOM07-IHM-01 | B12: IHM | C12: Élevée | D12: “Liste des documents à fournir” non définie. | E12: Quelle est la liste exacte des justificatifs attendus en V1 (types de documents) ? | F12: Cas de test incomplets | G12: A clarifier | H12: Elsa
... A43: TOM15-INT-01 | B43: API/Interco | C43: Élevée | D43: Page “prise de rendez-vous” non décrite. | E43: Existe‑t‑il déjà une page/service de RDV (URL, champs, calendrier) et quelles données sont transmises depuis l’assistant ? | F43: Blocage E2E sprint 5 | G43: A clarifier | H43: Elsa

Sheet Plan de test par Sprint
A1: Sprint | B1: ID | C1: Exigence | D1: Titre | E1: Criticité | F1: Type | G1: Statut
A2: Sprint 1 | B2: TC-S1-001 | C2: TOM01-AUT-01 | D2: Comptes & identités – règles V1 (unicité / multi-profils) | E2: Élevée | F2: Fonctionnel (E2E) | G2: Non exécuté
A3: Sprint 1 | B3: TC-S1-002 | C3: TOM01-DON-01 (Données/BDD) | D3: Création de compte – champs obligatoires/optionnels & conformité RGPD (données) | E3: Élevée | F3: Fonctionnel + Données | G3: Non exécuté
A4: Sprint 1 | B4: TC-S1-003 | C4: TOM01-DON-01 (Sécurité/Conformité) | D4: Session – déconnexion automatique après inactivité (timeout) | E4: Critique | F4: Sécurité (E2E) | G4: Non exécuté
A5: Sprint 1 | B5: TC-S1-004 | C5: TOM01-DON-01 (Sécurité/Conformité) ; TOM06-SEC-01 (Sécurité/Conformité) | D5: Authentification – verrouillage & anti-bruteforce après échecs | E5: Critique | F5: Sécurité (E2E) | G5: Non exécuté
A6: Sprint 1 | B6: TC-S1-005 | C6: TOM01-SEC-01 (Sécurité/Conformité) | D6: Audit – journalisation des événements sensibles (compte/MDP/2FA/biométrie) | E6: Élevée | F6: Sécurité / Audit | G6: Non exécuté
A7: Sprint 1 | B7: TC-S1-006 | C7: TOM01-SEC-01 (IHM) | D7: Création de compte – contrôle d’éligibilité (âge/pays/résidence) | E7: Élevée | F7: Fonctionnel (E2E) / Conformité | G7: Non exécuté
A8: Sprint 1 | B8: TC-S1-007 | C8: TOM06-DON-01 | D8: Données utilisateur – stockage autorisé vs interdit (RGPD) | E8: Élevée | F8: Données / Conformité | G8: Non exécuté
A9: Sprint 1 | B9: TC-S1-008 | C9: TOM06-FLD-01 | D9: Saisie Nom/Prénom – acceptation des caractères autorisés | E9: Critique | F9: Fonctionnel / Validation | G9: Non exécuté
A10: Sprint 1 | B10: TC-S1-009 | C10: TOM06-FLD-01 | D10: Saisie Nom/Prénom – rejet des valeurs invalides (numérique/injection/longueur) | E10: Critique | F10: Sécurité / Validation | G10: Non exécuté
A11: Sprint 1 | B11: TC-S1-010 | C11: TOM06-FLD-02 | D11: Date de naissance – format & contrôles de cohérence | E11: Élevée | F11: Fonctionnel / Validation | G11: Non exécuté
A12: Sprint 1 | B12: TC-S1-011 | C12: TOM06-SEC-01 | D12: Mot de passe – application des règles de complexité à la création | E12: Critique | F12: Sécurité / Fonctionnel | G12: Non exécuté
... A49: Sprint 5 | B49: TC-S5-003 | C49: TOM15-INT-01 | D49: Intégration RDV – URL/service, données transmises depuis l’assistant | E49: Élevée | F49: Intégration / Sécurité | G49: Non exécuté

Sheet Sprint 1
A1: ID | B1: Exigence | C1: Titre | D1: Description | E1: Préconditions | F1: Étapes | G1: Données | H1: Résultat attendu | I1: Criticité | J1: Type | K1: Statut
A2: TC-S1-001 | B2: TOM01-AUT-01 | C2: Comptes & identités – règles V1 (unicité / multi-profils) | D2: Valider la règle V1 de gestion des identités (un seul profil vs multi-profils) et le comportement en cas de tentative de création d’un second profil. | E2: Environnement de test disponible (web/app), comptes de test autorisés, accès aux logs applicatifs. • Règle V1 confirmée (un seul profil ou multi-profils) et données de test correspondantes. | F2: 1. Créer un compte avec un email de test (email_A). 2. Se déconnecter. 3. Tenter de créer un second compte/profil avec le même email (email_A) ou d’ajouter une seconde identité si l’UI le permet. 4. Observer le comportement (création refusée / profil additionnel créé / parcours alternatif). | G2: email_A=utilisateur.test+001@exemple.com Mot de passe conforme à la politique | H2: Le comportement correspond à la règle V1 validée : • Si mono-profil : création/refus explicite + message utilisateur ; aucune duplication en base. • Si multi-profil : profil additionnel créé avec séparation des données et traçabilité. | I2: Élevée | J2: Fonctionnel (E2E) | K2: Non exécuté
A3: TC-S1-002 | B3: TOM01-DON-01 (Données/BDD) | C3: Création de compte – champs obligatoires/optionnels & conformité RGPD (données) | D3: Vérifier la complétude des champs (obligatoires/optionnels), les validations côté UI/API et la persistance uniquement des données autorisées. | E3: Environnement de test disponible (web/app), comptes de test autorisés, accès aux logs applicatifs. Accès lecture aux logs/BDD (ou observabilité) pour vérifier les données persistées. • Liste des champs obligatoires/optionnels + données interdites de stockage (RGPD) disponible. | F3: 1. Ouvrir l’écran de création de compte. 2. Renseigner uniquement les champs obligatoires avec des valeurs valides. 3. Soumettre le formulaire. 4. Vérifier que le compte est créé. 5. Répéter en omettant 1 champ obligatoire (un par itération). 6. Contrôler en base/logs que seules les données autorisées sont stockées (pas de données interdites). | G3: Jeu 1 (valide) : email, téléphone, adresse (selon règles), nom/prénom, date de naissance… Jeu 2 (négatif) : omission d’un champ obligatoire | H3: • Création acceptée uniquement si tous les champs obligatoires sont présents et valides. • Messages d’erreur explicites en cas de champ manquant/invalidité. • Aucune donnée interdite RGPD n’est persistée (ni dans BDD, ni dans logs applicatifs). | I3: Élevée | J3: Fonctionnel + Données | K3: Non exécuté
A4: TC-S1-003 | B4: TOM01-DON-01 (Sécurité/Conformité) | C4: Session – déconnexion automatique après inactivité (timeout) | D4: Valider la déconnexion automatique après une période d’inactivité et le comportement de reprise. | E4: Environnement de test disponible (web/app), comptes de test autorisés, accès aux logs applicatifs. • Valeur de timeout session connue (T minutes) et observable (UI/logs). | F4: 1. Se connecter avec un compte valide. 2. Rester inactif pendant T minutes (ou simuler via configuration). 3. Interagir avec l’application (navigation / action). 4. Observer l’état de session et la redirection éventuelle. 5. Tenter une action nécessitant une session active. | G4: Compte valide (user_A) ; T = timeout configuré | H4: • À l’issue de T : session invalidée. • L’utilisateur est redirigé vers la connexion avec un message explicite. • Aucune action sensible n’est exécutée avec une session expirée. | I4: Critique | J4: Sécurité (E2E) | K4: Non exécuté
A5: TC-S1-004 | B5: TOM01-DON-01 (Sécurité/Conformité) ; TOM06-SEC-01 (Sécurité/Conformité) | C5: Authentification – verrouillage & anti-bruteforce après échecs | D5: Valider la politique de protection contre le bruteforce : nombre d’échecs avant blocage, durée, rate-limit/captcha et journalisation. | E5: Environnement de test disponible (web/app), comptes de test autorisés, accès aux logs applicatifs. • Un compte actif existe (user_A) et la politique de sécurité (N tentatives, durée, anti-bruteforce) est configurée. | F5: 1. Se rendre sur l’écran de connexion. 2. Saisir user_A avec un mot de passe incorrect. 3. Répéter jusqu’à atteindre le seuil d’échecs (N). 4. Tenter une connexion supplémentaire (mot de passe incorrect puis correct). 5. Vérifier le comportement (blocage / captcha / rate-limit) et le message affiché. 6. Attendre la durée de blocage (ou simuler l’expiration) puis retenter avec le mot de passe correct. 7. Vérifier la journalisation (événement de blocage, IP, horodatage). | G5: user_A=utilisateur.test+login@exemple.com MDP_incorrect=xxxxx MDP_correct=<conforme> | H5: • Après N échecs : accès refusé selon politique (blocage/captcha/rate-limit) + message clair. • Pendant blocage : même mot de passe correct est refusé. • Après expiration : connexion possible. • Événements de sécurité journalisés avec le niveau de détail attendu. | I5: Critique | J5: Sécurité (E2E) | K5: Non exécuté
A6: TC-S1-005 | B6: TOM01-SEC-01 (Sécurité/Conformité) | C6: Audit – journalisation des événements sensibles (compte/MDP/2FA/biométrie) | D6: Contrôler que les actions sensibles génèrent des événements d’audit complets et exploitables. | E6: Environnement de test disponible (web/app), comptes de test autorisés, accès aux logs applicatifs. • Accès aux logs/audit trail. • Liste des événements attendus disponible. | F6: 1. Créer un compte utilisateur. 2. Se connecter. 3. Changer le mot de passe. 4. Activer/désactiver 2FA. 5. Activer la biométrie (si disponible). 6. Vérifier dans l’audit trail la présence des événements, leur horodatage, l’identifiant utilisateur et le contexte (IP/device). | G6: Compte user_A ; actions sensibles ci-dessus | H6: Chaque action sensible produit un événement d’audit conforme : • type d’événement correct, userId, timestamp, source (IP/device), résultat (succès/échec). • Pas d’exposition de secrets (MDP, codes 2FA) dans les logs. | I6: Élevée | J6: Sécurité / Audit | K6: Non exécuté
A7: TC-S1-006 | B7: TOM01-SEC-01 (IHM) | C7: Création de compte – contrôle d’éligibilité (âge/pays/résidence) | D7: Vérifier que les règles d’éligibilité bloquent la création pour un utilisateur non éligible et guident l’utilisateur. | E7: Environnement de test disponible (web/app), comptes de test autorisés, accès aux logs applicatifs. • Règles d’éligibilité V1 connues (âge min, pays autorisés, résidence…). | F7: 1. Ouvrir l’écran de création de compte. 2. Saisir des données correspondant à un cas non éligible (ex. âge < min ou pays non autorisé). 3. Soumettre la demande. 4. Répéter avec un cas éligible. 5. Vérifier la traçabilité (audit) si applicable. | G7: Cas non éligible : âge=16 (si min=18) OU pays=XX non autorisé Cas éligible : âge>=min, pays autorisé | H7: • Cas non éligible : création refusée, message clair (raison + next step) ; aucune création en base. • Cas éligible : parcours continue/compte créé. | I7: Élevée | J7: Fonctionnel (E2E) / Conformité | K7: Non exécuté
A8: TC-S1-007 | B8: TOM06-DON-01 | C8: Données utilisateur – stockage autorisé vs interdit (RGPD) | D8: Vérifier la persistance des informations obligatoires et l’absence de stockage des données interdites (y compris cache/logs). | E8: Environnement de test disponible (web/app), comptes de test autorisés, accès aux logs applicatifs. Accès lecture aux logs/BDD (ou observabilité) pour vérifier les données persistées. • Règles de données autorisées/interdites disponibles. | F8: 1. Créer un compte avec un jeu de données complet. 2. Consulter les données persistées (BDD) et les logs applicatifs. 3. Vérifier les champs obligatoires stockés (et leur format). 4. Vérifier qu’aucune donnée interdite n’apparaît (BDD, logs, exports). | G8: Jeu de données complet (identité) + valeurs représentatives | H8: • Champs obligatoires présents et exacts. • Données interdites absentes partout (stockage & traces). • Formats conformes (ex. normalisation, encodage). | I8: Élevée | J8: Données / Conformité | K8: Non exécuté
A9: TC-S1-008 | B9: TOM06-FLD-01 | C9: Saisie Nom/Prénom – acceptation des caractères autorisés | D9: Valider que Nom/Prénom acceptent les caractères attendus (lettres, accents, traits d’union, espaces) et respectent les longueurs max. | E9: Environnement de test disponible (web/app), comptes de test autorisés, accès aux logs applicatifs. | F9: 1. Ouvrir l’écran de saisie identité. 2. Renseigner Nom/Prénom avec des valeurs valides (accents, tirets, espaces). 3. Soumettre. 4. Vérifier l’affichage et la persistance (si accessible). | G9: Nom=Durand‑Martin Prénom=Élodie Anne Longueur = max‑1 | H9: Les valeurs valides sont acceptées, affichées correctement (accents conservés) et enregistrées sans altération. | I9: Critique | J9: Fonctionnel / Validation | K9: Non exécuté
A10: TC-S1-009 | B10: TOM06-FLD-01 | C10: Saisie Nom/Prénom – rejet des valeurs invalides (numérique/injection/longueur) | D10: S’assurer que les champs Nom/Prénom rejettent les valeurs non conformes et protègent contre l’injection. | E10: Environnement de test disponible (web/app), comptes de test autorisés, accès aux logs applicatifs. | F10: 1. Ouvrir l’écran de saisie identité. 2. Saisir un prénom numérique (ex. 12345) et soumettre. 3. Saisir une chaîne avec caractères interdits (ex. <script>…</script>) et soumettre. 4. Saisir une valeur dépassant la longueur maximale et soumettre. 5. Vérifier les messages d’erreur et l’absence de création/enregistrement. | G10: Prénom=12345 Nom=<script>alert(1)</script> Nom=AAAA...(max+1) | H10: • Les valeurs invalides sont refusées avec un message clair. • Aucune injection n’est exécutée (affichage neutralisé/échappé). • Aucune donnée invalide n’est persistée. | I10: Critique | J10: Sécurité / Validation | K10: Non exécuté
A11: TC-S1-010 | B11: TOM06-FLD-02 | C11: Date de naissance – format & contrôles de cohérence | D11: Valider le format de saisie de la date de naissance et les contrôles (âge minimum, dates impossibles/futures). | E11: Environnement de test disponible (web/app), comptes de test autorisés, accès aux logs applicatifs. • Format officiel confirmé (ex. JJ/MM/AAAA) et âge minimum connu. | F11: 1. Ouvrir l’écran de saisie date de naissance. 2. Saisir une date au format attendu et soumettre. 3. Saisir une date au format non conforme et soumettre. 4. Saisir une date future et soumettre. 5. Saisir une date correspondant à un âge < minimum et soumettre. | G11: Valide: 15/04/1990 Invalide: 15/04.1990 Futur: 01/01/2100 Âge<min: 01/01/2012 | H11: • Format conforme accepté. • Formats non conformes rejetés. • Dates futures/impossibles rejetées. • Âge < minimum : création bloquée + message explicite. | I11: Élevée | J11: Fonctionnel / Validation | K11: Non exécuté
A12: TC-S1-011 | B12: TOM06-SEC-01 | C12: Mot de passe – application des règles de complexité à la création | D12: Vérifier que la politique mot de passe est appliquée (longueur, complexité, interdits) et que les messages d’erreur sont compréhensibles. | E12: Environnement de test disponible (web/app), comptes de test autorisés, accès aux logs applicatifs. • Politique MDP documentée (longueur min, classes de caractères, mots interdits, etc.). | F12: 1. Ouvrir la création de compte. 2. Saisir un mot de passe non conforme (trop court / sans majuscule / etc.) et soumettre. 3. Vérifier le message d’erreur. 4. Saisir un mot de passe conforme et soumettre. 5. Vérifier que le compte est créé et que le MDP n’est jamais affiché en clair (UI/logs). | G12: MDP_invalide: 'password' MDP_valide: 'A1!xxxxxx' | H12: • MDP non conforme refusé + message indiquant la règle manquante. • MDP conforme accepté. • Aucun secret n’est journalisé. | I12: Critique | J12: Sécurité / Fonctionnel | K12: Non exécuté
... A21: TC-S1-020 | B21: TOM09-BIO-02 | C21: Biométrie – fallback en cas d’échec/indisponibilité + limitation d’essais | D21: Valider le fallback (MDP + 2FA) et la gestion des échecs biométrie, ainsi que la compatibilité plateformes cibles. | E21: Environnement de test disponible (web/app), comptes de test autorisés, accès aux logs applicatifs. • Plateformes/OS cibles confirmés (iOS/Android…). • 2FA activée sur le compte. | F21: 1. Activer biométrie sur un appareil supporté. 2. Provoquer un échec biométrie (mauvaise empreinte/visage) jusqu’au seuil X. 3. Vérifier le fallback (saisie MDP puis 2FA si exigée). 4. Désactiver la biométrie au niveau OS (ou la rendre indisponible) et vérifier le parcours. 5. Répéter sur chaque plateforme/OS cible. | G21: Seuil X d’échecs (selon OS/politique) Compte user_A avec 2FA | H21: • Après X échecs/indisponibilité : fallback appliqué sans bloquer indûment. • Le fallback respecte la règle de sécurité (MDP + 2FA si requis). • Fonctionnement conforme sur les plateformes/OS cibles. | I21: Élevée | J21: Sécurité / Compatibilité | K21: Non exécuté

Sheet Sprint 2
A1: ID | B1: Exigence | C1: Titre | D1: Description | E1: Préconditions | F1: Étapes | G1: Données | H1: Résultat attendu | I1: Criticité | J1: Type | K1: Statut
A2: TC-S2-001 | B2: TOM02-API-01 | C2: Interconnexion banques – gestion des erreurs (timeout/HTTP) & banque non supportée | D2: Valider les messages utilisateur, les tentatives de retry et la journalisation en cas d’erreurs interconnexion, y compris banque non supportée. | E2: Environnement de test disponible (web/app), comptes de test autorisés, accès aux logs applicatifs. | F2: 1. Déclencher un rafraîchissement en simulant un timeout (banque ne répond pas). 2. Simuler une réponse erreur (ex. 500/503) et observer le comportement. 3. Vérifier le nombre de tentatives/retry (et délai) selon règle. 4. Tenter d’ajouter/ sélectionner une banque non supportée. 5. Vérifier le message et l’absence de connexion créée. 6. Vérifier la journalisation des erreurs sans données sensibles. | G2: Simulation erreurs (proxy/mocks) Banque non supportée : 'Banque X' | H2: • Erreurs gérées : message clair, pas de crash, retry conforme. • Banque non supportée : parcours bloqué/indisponible + message. • Les erreurs sont journalisées de façon exploitable et sans exposition de secrets. | I2: Critique | J2: Résilience / Intégration | K2: Non exécuté
A3: TC-S2-002 | B3: TOM02-API-01 | C3: Interconnexion banques – rafraîchissement des données & fréquence de mise à jour | D3: Vérifier que le rafraîchissement récupère les données bancaires et que la fréquence/horodatage de mise à jour est conforme (affichage “dernière maj”). | E3: Environnement de test disponible (web/app), comptes de test autorisés, accès aux logs applicatifs. • Au moins 1 banque supportée est connectée. • Règle de fréquence de mise à jour connue (ex. 1/jour, x/jour). | F3: 1. Ouvrir la page de synthèse des comptes connectés. 2. Noter l’horodatage “dernière maj” (si présent). 3. Déclencher un rafraîchissement. 4. Vérifier la mise à jour des soldes/transactions. 5. Redéclencher des rafraîchissements à des intervalles < fréquence autorisée et vérifier le comportement (réutilisation cache / refus / rate-limit). | G3: Banque supportée (ex. Banque A) Comptes avec transactions | H3: • Données mises à jour conformément à la fréquence attendue. • L’UI affiche un horodatage cohérent et un état (loader) pendant le refresh. • Les rafraîchissements trop fréquents sont gérés proprement (message, backoff, pas d’erreur). | I3: Critique | J3: Fonctionnel / Intégration | K3: Non exécuté
A4: TC-S2-003 | B4: TOM02-SEC-01 | C4: Consentement – obtention et stockage (standard OAuth2/PSD2) | D4: Vérifier l’obtention du consentement et le stockage/usage des jetons selon le standard retenu (OAuth2/PSD2). | E4: Environnement de test disponible (web/app), comptes de test autorisés, accès aux logs applicatifs. Accès lecture aux logs/BDD (ou observabilité) pour vérifier les données persistées. • Parcours de consentement activé et banque sandbox disponible. | F4: 1. Démarrer la connexion d’une banque. 2. Suivre le parcours d’autorisation (redirect/consent). 3. Confirmer l’accès et revenir à l’application. 4. Vérifier que la banque est connectée et que les données sont récupérées. 5. Vérifier en logs/BDD la présence d’un identifiant de consentement/jeton (sans secret en clair). | G4: Banque sandbox OAuth Utilisateur test | H4: • Consentement obtenu via le standard prévu. • Jetons/consentements stockés de manière sécurisée (pas en clair). • La connexion fonctionne immédiatement après consentement. | I4: Critique | J4: Sécurité / Intégration | K4: Non exécuté
A5: TC-S2-004 | B5: TOM02-SEC-01 | C5: Consentement – renouvellement, expiration et révocation | D5: Vérifier le comportement à l’expiration du consentement et la capacité de renouveler/révoquer proprement. | E5: Environnement de test disponible (web/app), comptes de test autorisés, accès aux logs applicatifs. • Durée de consentement connue et/ou possibilité de simuler une expiration. | F5: 1. Connecter une banque (consentement OK). 2. Simuler l’expiration du consentement (ou attendre). 3. Déclencher un rafraîchissement. 4. Vérifier que l’application déclenche un renouvellement (re-consent) ou affiche un message. 5. Révoquer le consentement (si option) et vérifier la déconnexion et l’arrêt des appels. | G5: Consentement expiré (simulation) Option révocation | H5: • À expiration : pas d’appels silencieux en échec ; UX guidée (renouveler). • Après renouvellement : données à nouveau accessibles. • Après révocation : banque déconnectée, plus d’accès, traçabilité. | I5: Critique | J5: Sécurité / Conformité | K5: Non exécuté
A6: TC-S2-005 | B6: TOM10-API-01 | C6: API – authentification des appels (TLS + mécanisme attendu) | D6: Vérifier que les appels API utilisent TLS et le mécanisme d’authentification prévu (API key/OAuth) et gèrent les erreurs d’auth. | E6: Environnement de test + outil d'appel API (Postman/Insomnia) + identifiants/clefs valides. | F6: 1. Appeler l’API avec en-têtes/auth valides. 2. Vérifier réponse 2xx et contenu. 3. Retirer/altérer l’authentification (clé manquante/jeton expiré). 4. Vérifier la réponse (401/403) et le message côté application. 5. Vérifier que les appels non-TLS sont refusés (si testable). | G6: Headers valides / invalides Token expiré | H6: • Appels valides acceptés. • Appels invalides refusés avec codes standards. • UX: message clair, pas de fuite d’infos. • TLS obligatoire. | I6: Critique | J6: API / Sécurité | K6: Non exécuté
A7: TC-S2-006 | B7: TOM10-DON-01 | C7: Données interconnexion – persistance (objets/champs) & conservation | D7: Contrôler que les objets interconnexion (banques, comptes, consentements, statuts) sont persistés avec les champs obligatoires et les durées de conservation configurées. | E7: Environnement de test disponible (web/app), comptes de test autorisés, accès aux logs applicatifs. Accès lecture aux logs/BDD (ou observabilité) pour vérifier les données persistées. • Modèle de données attendu (tables/champs obligatoires) disponible. | F7: 1. Connecter une banque et synchroniser des données. 2. Vérifier en BDD la création des enregistrements attendus (banque, compte, statut, consentement). 3. Vérifier la présence des champs obligatoires et l’absence de champs interdits. 4. Vérifier la présence d’un mécanisme/flag de conservation (date d’expiration/TTL) si applicable. | G7: Connexion Banque A Synchronisation données | H7: • Tous les objets attendus sont créés. • Champs obligatoires renseignés ; cohérence référentielle. • Les règles de conservation sont traçables (dates/TTL) selon spécification. | I7: Critique | J7: Données / Intégration | K7: Non exécuté
A8: TC-S2-007 | B8: TOM10-LIEN-01 | C8: Gouvernance – cohérence des dépendances & ticket parent | D8: Vérifier que le lien de dépendance et le ticket parent sont corrects (cohérence de périmètre). | E8: Accès au projet Jira et aux epics/tickets TOM concernés. | F8: 1. Ouvrir l’epic/ticket TOM10 dans Jira. 2. Vérifier le ticket parent référencé. 3. Vérifier les liens de dépendance (blocked by/depends on) et leur TOM associé. 4. Signaler toute incohérence (ex. parent TOM09 biométrie) et proposer correction. | G8: Tickets Jira TOM10 / TOM02 / TOM09 | H8: Les liens Jira (parent/dépendances) sont cohérents avec le périmètre (interconnexion) et corrigés en cas d’écart. | I8: Moyenne | J8: Processus / Gouvernance | K8: Non exécuté
A9: TC-S2-008 | B9: TOM10-NFR-01 | C9: NFR – limitation de fréquence (1 demande / 5 min) selon périmètre | D9: Valider la limitation de fréquence et son périmètre (par utilisateur/device/global). | E9: Environnement de test + outil d'appel API (Postman/Insomnia) + identifiants/clefs valides. • Règle de rate-limit confirmée (périmètre + fenêtre). | F9: 1. Exécuter une requête cible (endpoint concerné) avec user_A. 2. Répéter immédiatement la même requête depuis la même session. 3. Répéter depuis un autre device/session (si applicable). 4. Observer les codes de réponse (429/4xx) et les en-têtes de rate-limit. 5. Vérifier la remise à zéro après la fenêtre (5 min). | G9: Endpoint cible user_A, user_B Device A/B | H9: • Les requêtes au-delà de la limite sont refusées proprement (429 ou équivalent) avec indication de retry. • Le périmètre appliqué correspond à la règle V1. • Aucun impact inattendu sur d’autres utilisateurs. | I9: Élevée | J9: Performance / Sécurité | K9: Non exécuté
A10: TC-S2-009 | B10: TOM11-API-03 | C10: Données bancaires incomplètes – message utilisateur & calcul (solde partiel/dernier connu) | D10: Vérifier le comportement lorsque certaines banques ne renvoient pas de données : message, affichage partiel, fallback. | E10: Environnement de test disponible (web/app), comptes de test autorisés, accès aux logs applicatifs. • Au moins 2 banques connectées (Banque A OK, Banque B simulée en erreur). | F10: 1. Connecter Banque A et Banque B. 2. Simuler une absence de données pour Banque B. 3. Ouvrir la synthèse. 4. Vérifier le message d’avertissement et l’affichage (solde partiel / dernier solde connu) selon règle. 5. Déclencher un rafraîchissement et vérifier la persistance du message et la traçabilité. | G10: Banque A : OK Banque B : timeout/erreur | H10: • L’utilisateur est informé clairement des données manquantes. • L’application applique la règle de fallback attendue sans présenter de données trompeuses. • Les erreurs sont traçables. | I10: Élevée | J10: Fonctionnel / UX | K10: Non exécuté
A11: TC-S2-010 | B11: TOM11-IHM-01 | C11: IHM – bouton « Rafraîchir » (accessibilité, sticky) & loader/dernière maj | D11: Vérifier la visibilité du bouton, son accessibilité sans scroll excessif, et les états UI (loader, dernière maj). | E11: Environnement de test disponible (web/app), comptes de test autorisés, accès aux logs applicatifs. | F11: 1. Ouvrir la page contenant le bouton « Rafraîchir ». 2. Vérifier sa visibilité sur différents formats (mobile/desktop) sans scroller. 3. Cliquer sur « Rafraîchir ». 4. Vérifier l’apparition d’un loader, la désactivation du bouton pendant l’action, puis l’horodatage “dernière maj”. | G11: Résolutions: mobile/desktop | H11: • Bouton accessible (conforme UX) ; pas de parcours bloquant. • États loader et “dernière maj” cohérents. • Pas de double-submit. | I11: Élevée | J11: UX / Fonctionnel | K11: Non exécuté
A12: TC-S2-011 | B12: TOM11-IHM-02 | C12: IHM – ordre d’affichage des banques & comportement si 0 banque | D12: Vérifier l’ordre d’affichage des blocs banques et la gestion du cas « aucune banque connectée ». | E12: Environnement de test disponible (web/app), comptes de test autorisés, accès aux logs applicatifs. • Règle d’ordre confirmée (alpha, banque principale, dernier usage…). | F12: 1. Ouvrir la page des banques avec 3 banques connectées. 2. Vérifier l’ordre affiché. 3. Déconnecter toutes les banques. 4. Revenir à l’écran et vérifier le message/CTA (ex. « Connecter une banque »). | G12: Banques A/B/C Cas 0 banque | H12: • Ordre conforme à la règle. • Cas 0 banque : message clair + action possible ; aucun écran vide/confus. | I12: Moyenne | J12: UX / Fonctionnel | K12: Non exécuté
... A17: TC-S2-016 | B17: TOM12-IHM-02 | C17: Export relevés – multi-banques (ZIP/sélection) & parcours utilisateur | D17: Vérifier le comportement quand le service renvoie 1 PDF par banque : mode de téléchargement (ZIP, sélection, séquentiel) et UX associée. | E17: Environnement de test disponible (web/app), comptes de test autorisés, accès aux logs applicatifs. • Au moins 2 banques connectées et export multi-banques supporté. | F17: 1. Demander un export couvrant 2 banques. 2. Observer le résultat : fichier ZIP / sélection banque / téléchargements successifs. 3. Vérifier le message utilisateur et la gestion des erreurs partielles (1 banque OK, 1 KO). 4. Vérifier l’intégrité des fichiers téléchargés. | G17: Banque A + Banque B Période_ok | H17: • Le mode de téléchargement correspond à la règle V1. • Les fichiers sont intègres. • En cas d’erreur partielle : message clair + possibilité de relancer. | I17: Élevée | J17: Fonctionnel / UX | K17: Non exécuté

Sheet Sprint 3
A1: ID | B1: Exigence | C1: Titre | D1: Description | E1: Préconditions | F1: Étapes | G1: Données | H1: Résultat attendu | I1: Criticité | J1: Type | K1: Statut
A2: TC-S3-001 | B2: TOM03-DON-01 | C2: Consultation transactions – volumétrie & pagination (max affiché/chargé) | D2: Vérifier la volumétrie maximale affichée/chargée et la stratégie (pagination vs scroll) sans dégradation majeure. | E2: Environnement de test disponible (web/app), comptes de test autorisés, accès aux logs applicatifs. • Règle de volumétrie confirmée (N transactions) et stratégie (pagination/scroll). | F2: 1. Ouvrir l’écran de consultation des transactions. 2. Charger la liste jusqu’à atteindre N transactions (scroll/pagination). 3. Mesurer le temps de chargement et vérifier l’absence de freeze. 4. Vérifier que la liste n’excède pas N (ou qu’une pagination s’applique). 5. Vérifier la cohérence des données lors de navigation aller/retour. | G2: Compte avec >N transactions (jeu de données volumineux) | H2: • Chargement conforme à la stratégie. • La liste respecte N (ou pagination) et reste utilisable. • Pas de doublons/perte d’éléments lors du scroll/pagination. | I2: Moyenne | J2: Performance / Fonctionnel | K2: Non exécuté
A3: TC-S3-002 | B3: TOM03-IHM-01 | C3: Consultation transactions – filtres & tri (date/montant/banque/catégorie) | D3: Valider les filtres/tri requis et le comportement par défaut de l’historique. | E3: Environnement de test disponible (web/app), comptes de test autorisés, accès aux logs applicatifs. • Liste des filtres/tri requis confirmée + valeur par défaut attendue. | F3: 1. Ouvrir la consultation transactions. 2. Vérifier l’état par défaut (période/historique affiché). 3. Appliquer un filtre date (intervalle) et vérifier la liste. 4. Appliquer un filtre montant (>= / <=) et vérifier. 5. Filtrer par banque puis par catégorie. 6. Appliquer un tri (date desc/asc, montant) et vérifier la stabilité. 7. Réinitialiser filtres/tri. | G3: Jeu de transactions multi-banques et multi-catégories | H3: • Chaque filtre restreint correctement la liste. • Les tris ordonnent correctement sans incohérences. • L’état par défaut correspond à la règle. • Réinitialisation restaure l’état initial. | I3: Élevée | J3: Fonctionnel / UX | K3: Non exécuté
A4: TC-S3-003 | B4: TOM13-DON-01 | C4: Dernières transactions – zéro stockage (BDD/cache) & impact perf (repli/dépli) | D4: Vérifier que les dernières transactions ne sont pas stockées en BDD (ni cache persistant) et que le repli/dépli ne dégrade pas les performances. | E4: Environnement de test disponible (web/app), comptes de test autorisés, accès aux logs applicatifs. Accès lecture aux logs/BDD (ou observabilité) pour vérifier les données persistées. • Règle “zéro stockage” confirmée (ce qui est autorisé : cache mémoire temporaire). | F4: 1. Ouvrir l’écran affichant les dernières transactions. 2. Observer les appels réseau lors de l’affichage. 3. Replier/déplier le widget plusieurs fois. 4. Vérifier que le comportement est conforme (réutilisation mémoire vs refetch) selon règle. 5. Vérifier en BDD/logs qu’aucune transaction n’est persistée. 6. Vérifier qu’aucune donnée n’est écrite en stockage local persistant (LocalStorage/Cache). | G4: Compte avec transactions | H4: • Aucune persistance en BDD/cache persistant. • Perf acceptable lors des repli/dépli (pas d’explosion d’appels). • Le comportement (refetch vs cache mémoire) suit la règle V1. | I4: Moyenne | J4: Données / Performance | K4: Non exécuté
A5: TC-S3-004 | B5: TOM13-IHM-01 | C5: Dernières transactions – nombre affiché (10/50/100) & pagination | D5: Valider le nombre de transactions affichées par banque et la pagination éventuelle sur le composant « dernières transactions ». | E5: Environnement de test disponible (web/app), comptes de test autorisés, accès aux logs applicatifs. • N (10/50/100) et présence pagination confirmés. | F5: 1. Ouvrir le composant « dernières transactions » pour une banque. 2. Compter le nombre d’éléments affichés. 3. Si pagination : naviguer pages suivantes et vérifier la continuité. 4. Vérifier la cohérence avec le total et l’absence de doublons. | G5: Banque avec >N transactions | H5: • Nombre affiché conforme. • Pagination (si présente) fonctionne et garde la cohérence. • UX correcte (loader, fin de liste). | I5: Élevée | J5: Fonctionnel / UX | K5: Non exécuté

Sheet Sprint 4
A1: ID | B1: Exigence | C1: Titre | D1: Description | E1: Préconditions | F1: Étapes | G1: Données | H1: Résultat attendu | I1: Criticité | J1: Type | K1: Statut
A2: TC-S4-001 | B2: TOM04-DON-01 | C2: Catégorisation dépenses – liste catégories & source (banque vs moteur) | D2: Vérifier la liste des catégories (« types de dépense ») et la source de catégorisation (banque vs interne), ainsi que la cohérence des mappings. | E2: Environnement de test disponible (web/app), comptes de test autorisés, accès aux logs applicatifs. Accès lecture aux logs/BDD (ou observabilité) pour vérifier les données persistées. • Liste de catégories attendue + règles de mapping connues. | F2: 1. Importer/afficher un jeu de transactions multi-catégories. 2. Vérifier l’affectation d’une catégorie à chaque transaction. 3. Vérifier que la catégorie appartient à la liste autorisée (pas de valeurs libres non prévues). 4. Si la banque fournit une catégorie : vérifier la transformation/mapping. 5. Vérifier en BDD/logs la valeur stockée (id/label) et sa stabilité. | G2: Transactions avec catégories diverses (alimentation, transport, etc.) | H2: • Les catégories utilisées correspondent à la liste prévue. • Les mappings sont cohérents et reproductibles. • Les valeurs persistées sont stables (id/label). | I2: Élevée | J2: Données / Fonctionnel | K2: Non exécuté
A3: TC-S4-002 | B3: TOM04-IHM-01 | C3: Filtre période – définition (mois calendaire vs glissant vs start/end) | D3: Vérifier que la sélection de période suit la définition retenue et que l’UI l’exprime clairement. | E3: Environnement de test disponible (web/app), comptes de test autorisés, accès aux logs applicatifs. • Définition de la période confirmée (mois calendaire / glissant / date-à-date). | F3: 1. Ouvrir l’écran de suivi des dépenses. 2. Sélectionner une période (ex. Janvier). 3. Vérifier les dates de début/fin appliquées. 4. Comparer avec la définition attendue. 5. Tester un changement de période et vérifier mise à jour. | G3: Exemples de périodes: mois courant, mois précédent, intervalle custom | H3: • Les dates appliquées correspondent exactement à la définition. • L’utilisateur comprend la période sélectionnée (libellés clairs). • La mise à jour des résultats est correcte. | I3: Moyenne | J3: UX / Fonctionnel | K3: Non exécuté
A4: TC-S4-003 | B4: TOM14-DON-01 | C4: Camembert conso – règles de calcul (débits/crédits/remboursements) | D4: Valider les règles de calcul du camembert : inclusion/exclusion des crédits, gestion remboursements/annulations et cohérence des totaux. | E4: Environnement de test disponible (web/app), comptes de test autorisés, accès aux logs applicatifs. Accès lecture aux logs/BDD (ou observabilité) pour vérifier les données persistées. • Règles de calcul confirmées (débits uniquement ? crédits ? traitement refunds). | F4: 1. Charger un jeu de transactions incluant : débits, crédits, remboursement, annulation. 2. Afficher le camembert de consommation. 3. Vérifier quelles opérations sont incluses/exclues. 4. Vérifier que les montants par catégorie et le total correspondent aux règles. 5. Vérifier la cohérence avec la liste de transactions filtrée sur la même période. | G4: Jeu de données : • Débit 100€ (cat A) • Crédit 50€ • Remboursement -20€ • Annulation | H4: • Inclusion/exclusion conforme. • Totaux cohérents (camembert = somme des opérations retenues). • Remboursements/annulations traités selon règle sans incohérence. | I4: Élevée | J4: Données / Fonctionnel | K4: Non exécuté
A5: TC-S4-004 | B5: TOM14-IHM-01 | C5: Camembert conso – sélecteur date (unique/intervalle) & défaut | D5: Vérifier le sélecteur de période (date unique/intervalle) et la valeur par défaut (ex. mois courant). | E5: Environnement de test disponible (web/app), comptes de test autorisés, accès aux logs applicatifs. • Comportement attendu confirmé. | F5: 1. Ouvrir l’écran du camembert. 2. Vérifier la période par défaut. 3. Modifier la période via le sélecteur. 4. Vérifier que l’UI reflète le choix et que les données se recalculent. 5. Tester des bornes invalides (fin < début) si intervalle. | G5: Période par défaut Intervalle custom (si dispo) | H5: • Défaut conforme. • Changement de période recalculé correctement. • Valeurs invalides refusées avec message. | I5: Moyenne | J5: UX / Fonctionnel | K5: Non exécuté
A6: TC-S4-005 | B6: TOM14-NOM-01 | C6: Gouvernance – nom & périmètre TOM14 (cohérence documentation) | D6: Vérifier que le nom et le périmètre du TOM14 sont cohérents (titre vs contenu) dans les supports de référence. | E6: Accès au projet Jira et aux epics/tickets TOM concernés. | F6: 1. Ouvrir la documentation/epic TOM14. 2. Comparer le titre affiché avec le contenu (camembert suivi conso). 3. Identifier les incohérences (ex. titre « Interconnexions »). 4. Proposer la correction (renommage + description) et consigner l’écart. | G6: Docs/epic TOM14 | H6: Titre et périmètre du TOM14 corrigés/alignés sur le contenu réel (suivi conso camembert). | I6: Moyenne | J6: Processus / Gouvernance | K6: Non exécuté

Sheet Sprint 5
A1: ID | B1: Exigence | C1: Titre | D1: Description | E1: Préconditions | F1: Étapes | G1: Données | H1: Résultat attendu | I1: Criticité | J1: Type | K1: Statut
A2: TC-S5-001 | B2: TOM05-IHM-01 | C2: Aide utilisateur – accès (FAQ / contact / conseiller virtuel) selon périmètre V1 | D2: Vérifier les points d’entrée d’aide utilisateur et leur contenu selon le périmètre V1. | E2: Environnement de test disponible (web/app), comptes de test autorisés, accès aux logs applicatifs. • Périmètre V1 confirmé (FAQ, contact, conseiller virtuel…). | F2: 1. Ouvrir les écrans principaux (dashboard, transactions, paramètres). 2. Identifier les accès à l’aide (icône ?, menu, footer). 3. Vérifier que les liens ouvrent la bonne section (FAQ, contact, assistant). 4. Vérifier le comportement hors connexion (si applicable). | G2: Parcours multi-écrans | H2: Les accès à l’aide sont disponibles et cohérents avec le périmètre V1 ; les contenus/CTA sont corrects. | I2: Moyenne | J2: UX / Fonctionnel | K2: Non exécuté
A3: TC-S5-002 | B3: TOM15-IHM-01 | C3: Conseiller virtuel – recommandations V1 & scénario « redirection RDV » | D3: Valider les recommandations délivrées par l’assistant (types, contexte) et le fait que la conversation redirige vers la prise de RDV si prévu. | E3: Environnement de test disponible (web/app), comptes de test autorisés, accès aux logs applicatifs. • Catalogue de recommandations V1 confirmé (budget, épargne, opérations inhabituelles…). | F3: 1. Ouvrir le conseiller virtuel. 2. Déclencher un scénario de recommandation (ex. dépassement budget simulé). 3. Vérifier le contenu du message (clair, actionnable) et les choix proposés. 4. Déclencher un cas nécessitant RDV (selon règle). 5. Vérifier la redirection vers la page/flow de RDV (pas de “chat” non prévu). | G3: Scénario budget dépassé Scénario RDV (ex. besoin conseiller) | H3: • Recommandations conformes au catalogue V1. • UI conforme (assistant standard vs contextuel) selon décision. • Redirection RDV fonctionne lorsque prévu. | I3: Élevée | J3: UX / Fonctionnel | K3: Non exécuté
A4: TC-S5-003 | B4: TOM15-INT-01 | C4: Intégration RDV – URL/service, données transmises depuis l’assistant | D4: Vérifier l’intégration vers la prise de rendez-vous (URL/service) et les données passées (contexte, utilisateur) conformément à la spécification. | E4: Environnement de test disponible (web/app), comptes de test autorisés, accès aux logs applicatifs. • URL/service RDV disponible et spécification des champs transmise confirmée. | F4: 1. Depuis le conseiller virtuel, déclencher la redirection vers RDV. 2. Vérifier l’ouverture de l’URL/page RDV. 3. Vérifier les données pré-remplies transmises (si prévu) : identifiant utilisateur, motif, contexte. 4. Vérifier les erreurs (service indisponible) et le message de fallback. 5. Vérifier qu’aucune donnée sensible n’est transmise en clair dans l’URL. | G4: Motif RDV=« Besoin d’aide » Context=budget/banque UserId | H4: • Redirection RDV réussie. • Données transmises conformes (et minimisées). • En cas d’échec : message clair + alternative. • Pas de secrets en URL. | I4: Élevée | J4: Intégration / Sécurité | K4: Non exécuté

Sheet Visualisations
A1: Visualisations — QA (TOMSEN)
A2: Palette: Critique=rouge • Élevée=orange • Moyenne=jaune • Faible=vert • Informative=bleu
A3: Criticité | B3: Nb | D3: Sprint | E3: Nb
A4: Critique | B4: =COUNTIF('Plan de test par Sprint'!$E$2:$E$1000,"Critique") -> 16 | D4: Sprint 1 | E4: =COUNTIF('Plan de test par Sprint'!$A$2:$A$1000,"Sprint 1") -> 20
A5: Élevée | B5: =COUNTIF('Plan de test par Sprint'!$E$2:$E$1000,"Élevée") -> 22 | D5: Sprint 2 | E5: =COUNTIF('Plan de test par Sprint'!$A$2:$A$1000,"Sprint 2") -> 16
A6: Moyenne | B6: =COUNTIF('Plan de test par Sprint'!$E$2:$E$1000,"Moyenne") -> 10 | D6: Sprint 3 | E6: =COUNTIF('Plan de test par Sprint'!$A$2:$A$1000,"Sprint 3") -> 4
A7: Faible | B7: =COUNTIF('Plan de test par Sprint'!$E$2:$E$1000,"Faible") -> 0 | D7: Sprint 4 | E7: =COUNTIF('Plan de test par Sprint'!$A$2:$A$1000,"Sprint 4") -> 5
A8: Informative | B8: =COUNTIF('Plan de test par Sprint'!$E$2:$E$1000,"Informative") -> 0 | D8: Sprint 5 | E8: =COUNTIF('Plan de test par Sprint'!$A$2:$A$1000,"Sprint 5") -> 3
A10: Catégorie | B10: Non exécuté | C10: En cours | D10: Passé | E10: Échoué | F10: Bloqué | G10: NA
A11: Global | B11: =COUNTIF('Plan de test par Sprint'!$G$2:$G$1000,"Non exécuté") -> 48 | C11: =COUNTIF('Plan de test par Sprint'!$G$2:$G$1000,"En cours") -> 0 | D11: =COUNTIF('Plan de test par Sprint'!$G$2:$G$1000,"Passé") -> 0 | E11: =COUNTIF('Plan de test par Sprint'!$G$2:$G$1000,"Échoué") -> 0 | F11: =COUNTIF('Plan de test par Sprint'!$G$2:$G$1000,"Bloqué") -> 0 | G11: =COUNTIF('Plan de test par Sprint'!$G$2:$G$1000,"NA") -> 0
